tpt_script_generator/__about__.py
tpt_script_generator/__init__.py
tpt_script_generator/base_operator.py
tpt_script_generator/cmd.py
tpt_script_generator/ddl_operator.py
tpt_script_generator/load_operator.py
tpt_script_generator/schema.py
tpt_script_generator/script.py
tpt_script_generator/step.py
tpt_script_generator/template.py
tpt_script_generator/update_operator.py
tpt_script_generator/enums/__init__.py
tpt_script_generator/enums/ddl_operator.py
tpt_script_generator/enums/load_operator.py
tpt_script_generator/enums/update_operator.py
tpt_script_generator-0.0.7.dist-info/METADATA
tpt_script_generator-0.0.7.dist-info/WHEEL
tpt_script_generator-0.0.7.dist-info/licenses/LICENSE.txt
tpt_script_generator-0.0.7.dist-info/RECORD
