Metadata-Version: 2.3
Name: tpt-script-generator
Version: 0.0.7
Summary: A python pacakge for Teradata PT script builder
Project-URL: Documentation, https://github.com/rhasanm/tpt-script-generator#readme
Project-URL: Issues, https://github.com/rhasanm/tpt-script-generator/issues
Project-URL: Source, https://github.com/rhasanm/tpt-script-generator
Author-email: "Md. Rakibul Hasan" <hasanrakibul.masum@gmail.com>
License-Expression: MIT
License-File: LICENSE.txt
Classifier: Development Status :: 4 - Beta
Classifier: Programming Language :: Python
Classifier: Programming Language :: Python :: 3.8
Classifier: Programming Language :: Python :: 3.9
Classifier: Programming Language :: Python :: 3.10
Classifier: Programming Language :: Python :: 3.11
Classifier: Programming Language :: Python :: 3.12
Classifier: Programming Language :: Python :: Implementation :: CPython
Classifier: Programming Language :: Python :: Implementation :: PyPy
Requires-Python: >=3.8
